zmqcli/__main__.py
zmqcli/zmqcli.py
zmqcli-0.9.7.dist-info/entry_points.txt
zmqcli-0.9.7.dist-info/METADATA
zmqcli-0.9.7.dist-info/WHEEL
zmqcli-0.9.7.dist-info/RECORD
