Metadata-Version: 2.1
Name: zmqcli
Version: 0.9.7
Summary: A small but powerful command-line interface to ZeroMQ.
Home-page: https://gitlab.com/tamtamresearch-public/pypi/zmqcli
License: Unlicense
Keywords: ZeroMQ,CLI,ØMQ,0MQ,zmq
Author: TamTam Research s.r.o.
Maintainer: Roman Horenovsky
Requires-Python: >=3.7,<4.0
Classifier: Development Status :: 5 - Production/Stable
Classifier: Environment :: Console
Classifier: Intended Audience :: Developers
Classifier: License :: OSI Approved :: The Unlicense (Unlicense)
Classifier: License :: Other/Proprietary License
Classifier: Operating System :: OS Independent
Classifier: Programming Language :: Python :: 3
Classifier: Programming Language :: Python :: 3.7
Classifier: Programming Language :: Python :: 3.8
Classifier: Programming Language :: Python :: 3.9
Classifier: Programming Language :: Python :: 3.10
Classifier: Programming Language :: Python :: 3.11
Classifier: Topic :: System :: Networking
Classifier: Topic :: Utilities
Requires-Dist: argparse (>=1.4.0,<2.0.0)
Requires-Dist: pyzmq (>=25.0.0,<26.0.0)
Project-URL: Documentation, https://gitlab.com/tamtamresearch-public/pypi/zmqcli
Project-URL: Repository, https://gitlab.com/tamtamresearch-public/pypi/zmqcli
